{"type": "FeatureCollection", "features": [{"type": "Feature", "geometry": {"type": "LineString", "coordinates": [[-98.260356, 40.413078], [-98.259313, 40.413084], [-98.258508, 40.413054]]}, "properties": {"id": 14041786, "highway": "service", "maxspeed_raw": null, "maxspeed_mph": -1}}, {"type": "Feature", "geometry": {"type": "LineString", "coordinates": [[-98.243305, 40.412492], [-98.243144, 40.412488], [-98.242126, 40.412488], [-98.241446, 40.412488]]}, "properties": {"id": 14041791, "highway": "service", "maxspeed_raw": null, "maxspeed_mph": -1}}, {"type": "Feature", "geometry": {"type": "LineString", "coordinates": [[-98.260282, 40.406019], [-98.259679, 40.406], [-98.259404, 40.405953], [-98.259157, 40.405843], [-98.259061, 40.405729]]}, "properties": {"id": 14042136, "highway": "service", "maxspeed_raw": null, "maxspeed_mph": -1}}, {"type": "Feature", "geometry": {"type": "LineString", "coordinates": [[-98.261387, 40.399673], [-98.261187, 40.399686], [-98.260329, 40.399711]]}, "properties": {"id": 14042143, "highway": "service", "maxspeed_raw": null, "maxspeed_mph": -1}}, {"type": "Feature", "geometry": {"type": "LineString", "coordinates": [[-98.232765, 40.405169], [-98.232276, 40.405151], [-98.232096, 40.405135], [-98.232022, 40.405125], [-98.231983, 40.405077], [-98.23195, 40.404961], [-98.231931, 40.404875], [-98.231933, 40.404744]]}, "properties": {"id": 14042149, "highway": "service", "maxspeed_raw": null, "maxspeed_mph": -1}}, {"type": "Feature", "geometry": {"type": "LineString", "coordinates": [[-98.242381, 40.402687], [-98.242253, 40.402644], [-98.24192, 40.402619], [-98.241498, 40.4026]]}, "properties": {"id": 14042153, "highway": "service", "maxspeed_raw": null, "maxspeed_mph": -1}}, {"type": "Feature", "geometry": {"type": "LineString", "coordinates": [[-98.241504, 40.40208], [-98.241716, 40.402114], [-98.242039, 40.402181], [-98.242454, 40.402223], [-98.242832, 40.402255], [-98.243143, 40.402277], [-98.243457, 40.402289], [-98.243658, 40.402293], [-98.244151, 40.402293], [-98.244448, 40.402288], [-98.244558, 40.40226], [-98.244718, 40.402186], [-98.245113, 40.401962], [-98.245232, 40.401931], [-98.245501, 40.401929]]}, "properties": {"id": 14042156, "highway": "service", "maxspeed_raw": null, "maxspeed_mph": -1}}, {"type": "Feature", "geometry": {"type": "LineString", "coordinates": [[-98.244625, 40.393897], [-98.244653, 40.393523], [-98.244661, 40.393326], [-98.244908, 40.393144]]}, "properties": {"id": 14042157, "highway": "service", "maxspeed_raw": null, "maxspeed_mph": -1}}, {"type": "Feature", "geometry": {"type": "LineString", "coordinates": [[-98.222469, 40.408397], [-98.222204, 40.408393], [-98.22201, 40.408399], [-98.221962, 40.408443], [-98.221913, 40.408529], [-98.221921, 40.408647]]}, "properties": {"id": 14042159, "highway": "service", "maxspeed_raw": null, "maxspeed_mph": -1}}, {"type": "Feature", "geometry": {"type": "LineString", "coordinates": [[-98.260445, 40.384022], [-98.260666, 40.384019], [-98.260901, 40.384008], [-98.261037, 40.383983], [-98.261156, 40.383929], [-98.261245, 40.383824], [-98.261276, 40.383727], [-98.26125, 40.383351], [-98.261275, 40.383271], [-98.261387, 40.383238], [-98.26164, 40.383256]]}, "properties": {"id": 14042256, "highway": "service", "maxspeed_raw": null, "maxspeed_mph": -1}}, {"type": "Feature", "geometry": {"type": "LineString", "coordinates": [[-98.223445, 40.383681], [-98.223361, 40.383736], [-98.223259, 40.383761], [-98.22308, 40.38376], [-98.222716, 40.383773]]}, "properties": {"id": 14042270, "highway": "service", "maxspeed_raw": null, "maxspeed_mph": -1}}, {"type": "Feature", "geometry": {"type": "LineString", "coordinates": [[-98.22273, 40.382695], [-98.222395, 40.382689], [-98.222089, 40.38267], [-98.221903, 40.382633], [-98.220992, 40.382635], [-98.219605, 40.382674], [-98.219581, 40.382783], [-98.219574, 40.383404], [-98.219487, 40.383521]]}, "properties": {"id": 14042278, "highway": "service", "maxspeed_raw": null, "maxspeed_mph": -1}}, {"type": "Feature", "geometry": {"type": "LineString", "coordinates": [[-98.260441, 40.384748], [-98.260184, 40.384734], [-98.256713, 40.384766], [-98.256201, 40.384742], [-98.255964, 40.384757], [-98.25574, 40.384824], [-98.255521, 40.384915], [-98.255378, 40.385053]]}, "properties": {"id": 14042973, "highway": "service", "maxspeed_raw": null, "maxspeed_mph": -1}}, {"type": "Feature", "geometry": {"type": "LineString", "coordinates": [[-98.243683, 40.412502], [-98.243305, 40.412492], [-98.243444, 40.412626], [-98.243632, 40.412742], [-98.243748, 40.412746], [-98.243831, 40.412705], [-98.24389, 40.412629], [-98.243881, 40.412559], [-98.243823, 40.412528], [-98.243683, 40.412502]]}, "properties": {"id": 14043919, "highway": "service", "maxspeed_raw": null, "maxspeed_mph": -1}}, {"type": "Feature", "geometry": {"type": "LineString", "coordinates": [[-98.217874, 40.398806], [-98.217762, 40.398875], [-98.217769, 40.398789], [-98.217783, 40.398734], [-98.217852, 40.398708], [-98.217916, 40.398725], [-98.21792, 40.398764], [-98.217874, 40.398806]]}, "properties": {"id": 14044098, "highway": "service", "maxspeed_raw": null, "maxspeed_mph": -1}}, {"type": "Feature", "geometry": {"type": "LineString", "coordinates": [[-98.237652, 40.408061], [-98.237571, 40.407981], [-98.237454, 40.407831], [-98.237381, 40.40776]]}, "properties": {"id": 14044613, "highway": "service", "maxspeed_raw": null, "maxspeed_mph": -1}}, {"type": "Feature", "geometry": {"type": "LineString", "coordinates": [[-98.233063, 40.407048], [-98.233457, 40.406832], [-98.233621, 40.406797], [-98.233711, 40.406777], [-98.23411, 40.406758], [-98.234632, 40.406726], [-98.235306, 40.406714], [-98.236227, 40.406721]]}, "properties": {"id": 14044630, "highway": "service", "maxspeed_raw": null, "maxspeed_mph": -1}}, {"type": "Feature", "geometry": {"type": "LineString", "coordinates": [[-98.165498, 40.401244], [-98.169177, 40.401221], [-98.171166, 40.401231], [-98.174898, 40.401225], [-98.176462, 40.401216], [-98.179076, 40.401214], [-98.179598, 40.401208], [-98.180492, 40.401199], [-98.182235, 40.401207], [-98.182658, 40.401205], [-98.184034, 40.401199], [-98.184615, 40.4012], [-98.185255, 40.4012], [-98.186458, 40.401192], [-98.187254, 40.4012], [-98.190138, 40.401191], [-98.192165, 40.401179], [-98.197847, 40.401163], [-98.200056, 40.401161], [-98.203251, 40.40114], [-98.20354, 40.401141], [-98.207239, 40.401144], [-98.208046, 40.401139], [-98.209699, 40.401146], [-98.213622, 40.401143], [-98.217746, 40.401152], [-98.221271, 40.401152], [-98.222485, 40.401139]]}, "properties": {"id": 14044872, "highway": "unclassified", "maxspeed_raw": "50 mph", "maxspeed_mph": 50}}, {"type": "Feature", "geometry": {"type": "LineString", "coordinates": [[-98.2605814, 40.3503672], [-98.260551, 40.353415], [-98.260523, 40.35527], [-98.26053, 40.356674], [-98.260507, 40.357445], [-98.260506, 40.357576], [-98.260493, 40.360077], [-98.260479, 40.36143], [-98.260468, 40.36302], [-98.260456, 40.364867], [-98.26045, 40.365425], [-98.260471, 40.368351], [-98.260468, 40.369013], [-98.260469, 40.371878], [-98.260469, 40.373417], [-98.260483, 40.374714], [-98.260468, 40.376041], [-98.260479, 40.37667], [-98.260478, 40.379356], [-98.260478, 40.379379], [-98.26048, 40.379859], [-98.260454, 40.382168], [-98.260445, 40.384022], [-98.260441, 40.384748], [-98.260438, 40.385262], [-98.2604, 40.388249], [-98.260379, 40.391244], [-98.260355, 40.393875], [-98.260337, 40.397221], [-98.260329, 40.399711], [-98.260328, 40.400212], [-98.260299, 40.40288], [-98.260297, 40.403025], [-98.2603, 40.404335], [-98.260282, 40.406019], [-98.260281, 40.406211], [-98.2603087, 40.4081265]]}, "properties": {"id": 14046148, "highway": "tertiary", "maxspeed_raw": "50 mph", "maxspeed_mph": 50}}, {"type": "Feature", "geometry": {"type": "LineString", "coordinates": [[-98.241592, 40.35038], [-98.241605, 40.353857], [-98.241605, 40.354804], [-98.241605, 40.355412], [-98.241608, 40.357471], [-98.241617, 40.364882], [-98.241635, 40.365971], [-98.241626, 40.36728], [-98.241637, 40.370936], [-98.241631, 40.372001], [-98.241642, 40.372543], [-98.241649, 40.374828], [-98.241648, 40.375094], [-98.241645, 40.37621], [-98.241657, 40.379425], [-98.241644, 40.380617], [-98.24163, 40.381853], [-98.241625, 40.382278], [-98.241636, 40.383395], [-98.241635, 40.38344], [-98.241591, 40.385303], [-98.241578, 40.38648], [-98.241545, 40.388307], [-98.241546, 40.388769], [-98.241486, 40.392508], [-98.241477, 40.393887], [-98.241471, 40.39437], [-98.241475, 40.395072], [-98.241504, 40.396792], [-98.241501, 40.398495], [-98.2415, 40.399304], [-98.241509, 40.401679], [-98.241504, 40.40208], [-98.241498, 40.4026], [-98.241497, 40.402701], [-98.241511, 40.403035], [-98.241543, 40.403446], [-98.241535, 40.4036], [-98.241512, 40.403674], [-98.241485, 40.403758], [-98.241278, 40.404172], [-98.2412419, 40.404256]]}, "properties": {"id": 14046268, "highway": "unclassified", "maxspeed_raw": "50 mph", "maxspeed_mph": 50}}, {"type": "Feature", "geometry": {"type": "LineString", "coordinates": [[-98.236218, 40.404789], [-98.236221, 40.405118], [-98.236205, 40.405974], [-98.236251, 40.406103], [-98.23636, 40.406103], [-98.236835, 40.406329], [-98.237518, 40.406646], [-98.238432, 40.407089], [-98.239655, 40.4077], [-98.240915, 40.40832], [-98.24127, 40.408541], [-98.2414, 40.408742], [-98.241427, 40.408927], [-98.241427, 40.409505], [-98.241414, 40.410112], [-98.241446, 40.412488], [-98.241446, 40.412848], [-98.241445, 40.418564], [-98.241432, 40.419655], [-98.241428, 40.421602], [-98.241434, 40.4229], [-98.24143, 40.424631], [-98.241434, 40.425864], [-98.241432, 40.427661], [-98.24142, 40.428347], [-98.241415, 40.428662], [-98.241418, 40.432051], [-98.241406, 40.434246], [-98.241405, 40.435569], [-98.241407, 40.437374], [-98.241447, 40.442805], [-98.241455, 40.4458], [-98.241463, 40.446675], [-98.241469, 40.449878], [-98.241464, 40.450828], [-98.241478, 40.451903], [-98.241485, 40.452163], [-98.241463, 40.457871], [-98.241466, 40.459201], [-98.241473, 40.462119], [-98.241484, 40.466411], [-98.241494, 40.469986], [-98.241489, 40.473015], [-98.241473, 40.476045], [-98.241481, 40.479091], [-98.241478, 40.4795], [-98.241467, 40.480936], [-98.241459, 40.482099], [-98.24147, 40.49121], [-98.2414949, 40.494322], [-98.2415253, 40.4944269], [-98.2416242, 40.4945374]]}, "properties": {"id": 14046300, "highway": "unclassified", "maxspeed_raw": "50 mph", "maxspeed_mph": 50}}, {"type": "Feature", "geometry": {"type": "LineString", "coordinates": [[-98.222576, 40.350364], [-98.222594, 40.354606], [-98.222593, 40.355708], [-98.222589, 40.356021], [-98.222592, 40.356378], [-98.2226, 40.357133], [-98.222617, 40.360142], [-98.22262, 40.361713], [-98.22262, 40.361893], [-98.222622, 40.363167], [-98.222633, 40.364892], [-98.222634, 40.365604], [-98.22265, 40.366669], [-98.222678, 40.369694], [-98.222679, 40.369928], [-98.222681, 40.370767], [-98.222699, 40.372108], [-98.222707, 40.372707], [-98.222729, 40.374871], [-98.222768, 40.377708], [-98.222763, 40.380699], [-98.222748, 40.381593], [-98.22273, 40.382695], [-98.222716, 40.383773], [-98.222653, 40.387168], [-98.22262, 40.388499], [-98.222592, 40.390386], [-98.222563, 40.39148], [-98.22252, 40.393094], [-98.22251, 40.393903], [-98.222497, 40.395079], [-98.2225112, 40.3972043]]}, "properties": {"id": 14046348, "highway": "unclassified", "maxspeed_raw": "50 mph", "maxspeed_mph": 50}}, {"type": "Feature", "geometry": {"type": "LineString", "coordinates": [[-98.278029, 40.393789], [-98.277766, 40.393789], [-98.276778, 40.393801], [-98.276646, 40.393803], [-98.274581, 40.39381], [-98.273893, 40.393809], [-98.273847, 40.393809], [-98.272926, 40.393808], [-98.2719, 40.393819], [-98.268899, 40.393842], [-98.26795, 40.393846], [-98.266076, 40.393852], [-98.26541, 40.393854], [-98.264379, 40.393864], [-98.263782, 40.393863], [-98.261626, 40.393859], [-98.260671, 40.393874], [-98.260355, 40.393875], [-98.258803, 40.393879], [-98.257412, 40.393887], [-98.255242, 40.393878], [-98.251664, 40.39388], [-98.25056, 40.393887], [-98.249671, 40.393893], [-98.246364, 40.393899], [-98.245974, 40.3939], [-98.244625, 40.393897], [-98.242457, 40.393894], [-98.241477, 40.393887], [-98.239754, 40.39388], [-98.236016, 40.393899], [-98.23501, 40.393895], [-98.23466, 40.393894], [-98.232075, 40.393902], [-98.230445, 40.3939], [-98.229317, 40.39391], [-98.228448, 40.393897], [-98.22826, 40.393894], [-98.227042, 40.39389], [-98.2254, 40.393901], [-98.224421, 40.393898], [-98.22251, 40.393903]]}, "properties": {"id": 14047310, "highway": "unclassified", "maxspeed_raw": "50 mph", "maxspeed_mph": 50}}, {"type": "Feature", "geometry": {"type": "LineString", "coordinates": [[-98.248055, 40.405816], [-98.247453, 40.405786], [-98.246262, 40.405775], [-98.244847, 40.405746], [-98.244145, 40.405745], [-98.24399, 40.405717], [-98.243577, 40.405512], [-98.243354, 40.405412], [-98.243181, 40.405365], [-98.242899, 40.405318], [-98.242753, 40.405278], [-98.242571, 40.405195], [-98.242404, 40.405059], [-98.242119, 40.404838], [-98.241811, 40.404613], [-98.241458, 40.404392], [-98.2412419, 40.404256], [-98.24112, 40.4044391], [-98.2409274, 40.404707]]}, "properties": {"id": 14047349, "highway": "unclassified", "maxspeed_raw": "50 mph", "maxspeed_mph": 50}}, {"type": "Feature", "geometry": {"type": "LineString", "coordinates": [[-98.2409274, 40.404707], [-98.2406964, 40.4049839]]}, "properties": {"id": 368765962, "highway": "unclassified", "maxspeed_raw": "50 mph", "maxspeed_mph": 50}}, {"type": "Feature", "geometry": {"type": "LineString", "coordinates": [[-98.2406964, 40.4049839], [-98.2406245, 40.4050332], [-98.240557, 40.405053], [-98.240402, 40.405052], [-98.240294, 40.405013], [-98.239861, 40.404821], [-98.239664, 40.40479], [-98.239067, 40.404782], [-98.238118, 40.404776], [-98.236571, 40.404774], [-98.236218, 40.404789], [-98.234798, 40.404767], [-98.233686, 40.404758], [-98.231933, 40.404744], [-98.23132, 40.40474], [-98.227695, 40.404768], [-98.226494, 40.4047847]]}, "properties": {"id": 368765963, "highway": "unclassified", "maxspeed_raw": "50 mph", "maxspeed_mph": 50}}, {"type": "Feature", "geometry": {"type": "LineString", "coordinates": [[-98.2603087, 40.4081265], [-98.2603032, 40.4085814]]}, "properties": {"id": 368765965, "highway": "tertiary", "maxspeed_raw": "50 mph", "maxspeed_mph": 50}}, {"type": "Feature", "geometry": {"type": "LineString", "coordinates": [[-98.2603032, 40.4085814], [-98.260309, 40.409476], [-98.260311, 40.411406], [-98.26036, 40.412344], [-98.260356, 40.413078], [-98.260354, 40.413409], [-98.260378, 40.416054], [-98.260376, 40.417287], [-98.260383, 40.418292], [-98.260375, 40.420147], [-98.260398, 40.421296], [-98.260378, 40.422504], [-98.260387, 40.422885], [-98.260412, 40.424283], [-98.260419, 40.42629], [-98.260432, 40.427278], [-98.260434, 40.429809], [-98.260447, 40.430248], [-98.260478, 40.434256], [-98.260484, 40.434984], [-98.260494, 40.436137], [-98.2605057, 40.4373653]]}, "properties": {"id": 368765969, "highway": "tertiary", "maxspeed_raw": "50 mph", "maxspeed_mph": 50}}, {"type": "Feature", "geometry": {"type": "LineString", "coordinates": [[-98.2225112, 40.3972043], [-98.2225017, 40.3976987]]}, "properties": {"id": 368765972, "highway": "unclassified", "maxspeed_raw": "50 mph", "maxspeed_mph": 50}}, {"type": "Feature", "geometry": {"type": "LineString", "coordinates": [[-98.2225017, 40.3976987], [-98.222503, 40.39923], [-98.222485, 40.401139], [-98.222467, 40.404788], [-98.222469, 40.408397], [-98.22244, 40.413979], [-98.22244, 40.414272], [-98.222443, 40.416047], [-98.222444, 40.416273], [-98.222424, 40.417488], [-98.222427, 40.419251], [-98.222412, 40.42295], [-98.222412, 40.423175], [-98.222402, 40.42353], [-98.222403, 40.426547], [-98.222392, 40.429054], [-98.222398, 40.429598], [-98.222397, 40.430128], [-98.222396, 40.430628], [-98.222391, 40.433843], [-98.222394, 40.435631], [-98.222383, 40.437103], [-98.222395, 40.437447], [-98.222406, 40.437745], [-98.222386, 40.444713], [-98.222363, 40.451116], [-98.222371, 40.451971], [-98.222369, 40.452592], [-98.222357, 40.455269], [-98.22236, 40.455693], [-98.222355, 40.457437], [-98.222347, 40.461774], [-98.222343, 40.463594], [-98.222348, 40.466512], [-98.222345, 40.46722], [-98.222357, 40.469834], [-98.22237, 40.470249], [-98.222377, 40.473274], [-98.22236, 40.476295], [-98.22235, 40.479285], [-98.222338, 40.480787], [-98.222366, 40.480971], [-98.2223099, 40.4811995], [-98.2223441, 40.4849377]]}, "properties": {"id": 368765973, "highway": "unclassified", "maxspeed_raw": "50 mph", "maxspeed_mph": 50}}, {"type": "Feature", "geometry": {"type": "LineString", "coordinates": [[-98.237381, 40.40776], [-98.237292, 40.407739], [-98.237091, 40.407726], [-98.236258, 40.407715], [-98.236239, 40.40764], [-98.236205, 40.40738], [-98.236225, 40.406928], [-98.236227, 40.406721], [-98.23625, 40.406612], [-98.236254, 40.406274], [-98.236251, 40.406103]]}, "properties": {"id": 669910880, "highway": "unclassified", "maxspeed_raw": "50 mph", "maxspeed_mph": 50}}, {"type": "Feature", "geometry": {"type": "LineString", "coordinates": [[-98.2263155, 40.4047869], [-98.222798, 40.404795], [-98.222467, 40.404788]]}, "properties": {"id": 669910881, "highway": "unclassified", "maxspeed_raw": "50 mph", "maxspeed_mph": 50}}, {"type": "Feature", "geometry": {"type": "LineString", "coordinates": [[-98.226494, 40.4047847], [-98.2263155, 40.4047869]]}, "properties": {"id": 669910882, "highway": "unclassified", "maxspeed_raw": "50 mph", "maxspeed_mph": 50}}]}